[
  {
    "suite": "Parse CRUD",
    "test": "create_get_list_update_delete",
    "api_call": {
      "request": {
        "headers": {
          "X-Parse-Application-Id": "J7PyWtrIOUDTIvDXzpZD3WmJEn7zR6pXZmIIMlHW",
          "X-Parse-REST-API-Key": "jwnEHrsSIB5ZBqK9ILvxPav9FBxKtCHLgOsDGDFv",
          "Content-Type": "application/json"
        },
        "method": "POST",
        "params": {
          "score": 1337,
          "playerName": "Joe Johnson",
          "cheatMode": false
        },
        "url": "https://api.parse.com/1/classes/GameScore"
      },
      "status": 201,
      "assert": {
        "select": "body",
        "schema": {
          "type": "object",
          "properties": {
            "createdAt": {
              "type": "string"
            },
            "objectId": {
              "type": "string"
            }
          },
          "required": [
            "createdAt",
            "objectId"
          ],
          "additionalProperties": false
        }
      },
      "save": {
        "users.joe.objectId": "body.objectId"
      }
    },
    "response": {
      "status": 201,
      "headers": {
        "access-control-allow-methods": "*",
        "access-control-allow-origin": "*",
        "cache-control": "no-cache",
        "content-type": "application/json; charset=utf-8",
        "date": "Wed, 12 Nov 2014 22:27:00 GMT",
        "location": "https://api.parse.com/1/classes/GameScore/RMKeCP61bE",
        "server": "nginx/1.6.0",
        "set-cookie": [
          "_parse_session=BAh7BkkiD3Nlc3Npb25faWQGOgZFRiIlYjY3NDkzYjhmOTk4MThhNTU2ODFlNDUyMTJmNGJiZDc%3D--cf801019dc517747fbfd7f561cb12207fe49222f; domain=.parse.com; path=/; expires=Fri, 12-Dec-2014 22:27:00 GMT; secure; HttpOnly"
        ],
        "status": "201 Created",
        "x-content-type-options": "nosniff",
        "x-runtime": "0.172766",
        "x-ua-compatible": "IE=Edge,chrome=1",
        "content-length": "64",
        "connection": "keep-alive"
      },
      "body": {
        "createdAt": "2014-11-12T22:26:59.949Z",
        "objectId": "RMKeCP61bE"
      },
      "response_time": 1214
    },
    "errors": []
  },
  {
    "suite": "Parse CRUD",
    "test": "create_get_list_update_delete",
    "api_call": {
      "request": {
        "headers": {
          "X-Parse-Application-Id": "J7PyWtrIOUDTIvDXzpZD3WmJEn7zR6pXZmIIMlHW",
          "X-Parse-REST-API-Key": "jwnEHrsSIB5ZBqK9ILvxPav9FBxKtCHLgOsDGDFv"
        },
        "url": "https://api.parse.com/1/classes/GameScore/RMKeCP61bE",
        "method": "GET"
      },
      "status": 200,
      "assert": [
        {
          "select": "body",
          "schema": {
            "type": "object",
            "properties": {
              "cheatMode": {
                "type": "boolean"
              },
              "objectId": {
                "type": "string",
                "pattern": "^[a-zA-Z0-9]{10}$"
              },
              "playerName": {
                "type": "string"
              },
              "score": {
                "type": "integer"
              },
              "createdAt": {
                "type": "string",
                "format": "date-time"
              },
              "updatedAt": {
                "type": "string",
                "format": "date-time"
              }
            },
            "required": [
              "objectId",
              "playerName",
              "score"
            ]
          }
        },
        {
          "select": "body",
          "equal_keys": {
            "score": 1337,
            "playerName": "Joe Johnson",
            "cheatMode": false,
            "objectId": "RMKeCP61bE"
          }
        }
      ]
    },
    "response": {
      "status": 200,
      "headers": {
        "access-control-allow-methods": "*",
        "access-control-allow-origin": "*",
        "content-type": "application/json; charset=utf-8",
        "date": "Wed, 12 Nov 2014 22:27:00 GMT",
        "server": "nginx/1.6.0",
        "x-parse-platform": "G1",
        "x-runtime": "0.011589",
        "content-length": "162",
        "connection": "keep-alive"
      },
      "body": {
        "cheatMode": false,
        "createdAt": "2014-11-12T22:26:59.949Z",
        "objectId": "RMKeCP61bE",
        "playerName": "Joe Johnson",
        "score": 1337,
        "updatedAt": "2014-11-12T22:26:59.949Z"
      },
      "response_time": 622
    },
    "errors": []
  },
  {
    "suite": "Parse CRUD",
    "test": "create_get_list_update_delete",
    "api_call": {
      "request": {
        "headers": {
          "X-Parse-Application-Id": "J7PyWtrIOUDTIvDXzpZD3WmJEn7zR6pXZmIIMlHW",
          "X-Parse-REST-API-Key": "jwnEHrsSIB5ZBqK9ILvxPav9FBxKtCHLgOsDGDFv"
        },
        "params": {
          "order": "-created_at",
          "limit": 3
        },
        "url": "https://api.parse.com/1/classes/GameScore",
        "method": "GET"
      },
      "status": 200,
      "assert": [
        {
          "select": "body.results.0",
          "schema": {
            "type": "object",
            "properties": {
              "cheatMode": {
                "type": "boolean"
              },
              "objectId": {
                "type": "string",
                "pattern": "^[a-zA-Z0-9]{10}$"
              },
              "playerName": {
                "type": "string"
              },
              "score": {
                "type": "integer"
              },
              "createdAt": {
                "type": "string",
                "format": "date-time"
              },
              "updatedAt": {
                "type": "string",
                "format": "date-time"
              }
            },
            "required": [
              "objectId",
              "playerName",
              "score"
            ]
          }
        },
        {
          "select": "body.results",
          "size": 3
        },
        {
          "select": "body.results.0.objectId",
          "equal": "RMKeCP61bE"
        }
      ]
    },
    "response": {
      "status": 200,
      "headers": {
        "access-control-allow-methods": "*",
        "access-control-allow-origin": "*",
        "cache-control": "max-age=0, private, must-revalidate",
        "content-type": "application/json; charset=utf-8",
        "date": "Wed, 12 Nov 2014 22:27:01 GMT",
        "etag": "\"64d623267f107246be322868476d75d3\"",
        "server": "nginx/1.6.0",
        "set-cookie": [
          "_parse_session=BAh7BkkiD3Nlc3Npb25faWQGOgZFRiIlMTQ1ZjVlN2M1N2YxNmEyYzA3OTQzZmRiNTUzZmZlYzA%3D--29085a7eff6978d6993548fb98bd9e3ef30cc19a; domain=.parse.com; path=/; expires=Fri, 12-Dec-2014 22:27:01 GMT; secure; HttpOnly"
        ],
        "status": "200 OK",
        "x-content-type-options": "nosniff",
        "x-runtime": "0.041137",
        "x-ua-compatible": "IE=Edge,chrome=1",
        "content-length": "499",
        "connection": "keep-alive"
      },
      "body": {
        "results": [
          {
            "score": 1337,
            "playerName": "Joe Johnson",
            "cheatMode": false,
            "createdAt": "2014-11-12T22:26:59.949Z",
            "updatedAt": "2014-11-12T22:26:59.949Z",
            "objectId": "RMKeCP61bE"
          },
          {
            "score": 1337,
            "playerName": "Joe Johnson",
            "cheatMode": false,
            "createdAt": "2014-11-09T20:58:28.521Z",
            "updatedAt": "2014-11-09T20:58:28.521Z",
            "objectId": "ONsAuaThLe"
          },
          {
            "score": 1337,
            "playerName": "Joe Johnson",
            "cheatMode": false,
            "createdAt": "2014-11-09T20:25:58.063Z",
            "updatedAt": "2014-11-09T20:25:58.063Z",
            "objectId": "xAvH422nFP"
          }
        ]
      },
      "response_time": 630
    },
    "errors": []
  },
  {
    "suite": "Parse CRUD",
    "test": "create_get_list_update_delete",
    "api_call": {
      "request": {
        "headers": {
          "X-Parse-Application-Id": "J7PyWtrIOUDTIvDXzpZD3WmJEn7zR6pXZmIIMlHW",
          "X-Parse-REST-API-Key": "jwnEHrsSIB5ZBqK9ILvxPav9FBxKtCHLgOsDGDFv",
          "Content-Type": "application/json"
        },
        "method": "PUT",
        "params": {
          "playerName": "New name"
        },
        "url": "https://api.parse.com/1/classes/GameScore/RMKeCP61bE"
      },
      "status": 200
    },
    "response": {
      "status": 200,
      "headers": {
        "access-control-allow-methods": "*",
        "access-control-allow-origin": "*",
        "content-type": "application/json; charset=utf-8",
        "date": "Wed, 12 Nov 2014 22:27:02 GMT",
        "server": "nginx/1.6.0",
        "x-parse-platform": "G1",
        "x-runtime": "0.017280",
        "content-length": "41",
        "connection": "keep-alive"
      },
      "body": {
        "updatedAt": "2014-11-12T22:27:02.139Z"
      },
      "response_time": 771
    },
    "errors": []
  },
  {
    "suite": "Parse CRUD",
    "test": "create_get_list_update_delete",
    "api_call": {
      "request": {
        "headers": {
          "X-Parse-Application-Id": "J7PyWtrIOUDTIvDXzpZD3WmJEn7zR6pXZmIIMlHW",
          "X-Parse-REST-API-Key": "jwnEHrsSIB5ZBqK9ILvxPav9FBxKtCHLgOsDGDFv"
        },
        "url": "https://api.parse.com/1/classes/GameScore/RMKeCP61bE",
        "method": "GET"
      },
      "status": 200,
      "assert": {
        "select": "body.playerName",
        "equal": "New name"
      }
    },
    "response": {
      "status": 200,
      "headers": {
        "access-control-allow-methods": "*",
        "access-control-allow-origin": "*",
        "content-type": "application/json; charset=utf-8",
        "date": "Wed, 12 Nov 2014 22:27:02 GMT",
        "server": "nginx/1.6.0",
        "x-parse-platform": "G1",
        "x-runtime": "0.009358",
        "content-length": "159",
        "connection": "keep-alive"
      },
      "body": {
        "cheatMode": false,
        "createdAt": "2014-11-12T22:26:59.949Z",
        "objectId": "RMKeCP61bE",
        "playerName": "New name",
        "score": 1337,
        "updatedAt": "2014-11-12T22:27:02.139Z"
      },
      "response_time": 590
    },
    "errors": []
  },
  {
    "suite": "Parse CRUD",
    "test": "create_get_list_update_delete",
    "api_call": {
      "request": {
        "headers": {
          "X-Parse-Application-Id": "J7PyWtrIOUDTIvDXzpZD3WmJEn7zR6pXZmIIMlHW",
          "X-Parse-REST-API-Key": "jwnEHrsSIB5ZBqK9ILvxPav9FBxKtCHLgOsDGDFv"
        },
        "method": "DELETE",
        "url": "https://api.parse.com/1/classes/GameScore/RMKeCP61bE"
      },
      "status": 200
    },
    "response": {
      "status": 200,
      "headers": {
        "access-control-allow-methods": "*",
        "access-control-allow-origin": "*",
        "content-type": "application/json; charset=utf-8",
        "date": "Wed, 12 Nov 2014 22:27:03 GMT",
        "server": "nginx/1.6.0",
        "x-parse-platform": "G1",
        "x-runtime": "0.012656",
        "content-length": "3",
        "connection": "keep-alive"
      },
      "body": {},
      "response_time": 612
    },
    "errors": []
  },
  {
    "suite": "Parse CRUD",
    "test": "create_get_list_update_delete",
    "api_call": {
      "request": {
        "headers": {
          "X-Parse-Application-Id": "J7PyWtrIOUDTIvDXzpZD3WmJEn7zR6pXZmIIMlHW",
          "X-Parse-REST-API-Key": "jwnEHrsSIB5ZBqK9ILvxPav9FBxKtCHLgOsDGDFv"
        },
        "url": "https://api.parse.com/1/classes/GameScore/RMKeCP61bE",
        "method": "GET"
      },
      "status": 404
    },
    "response": {
      "status": 404,
      "headers": {
        "access-control-allow-methods": "*",
        "access-control-allow-origin": "*",
        "content-type": "application/json; charset=utf-8",
        "date": "Wed, 12 Nov 2014 22:27:03 GMT",
        "server": "nginx/1.6.0",
        "x-parse-platform": "G1",
        "x-runtime": "0.016580",
        "content-length": "48",
        "connection": "keep-alive"
      },
      "body": {
        "code": 101,
        "error": "object not found for get"
      },
      "response_time": 617
    },
    "errors": []
  }
]